Metadata-Version: 2.1
Name: cpm-cli
Version: 1.11.2
Summary: Chromos Package Manager
Home-page: https://github.com/jorsanpe/cpm
Author: Jordi Sánchez
License: UNKNOWN
Platform: UNKNOWN
Classifier: Development Status :: 5 - Production/Stable
Classifier: Environment :: Console
Classifier: Programming Language :: Python :: 3
Classifier: Programming Language :: C++
Classifier: Programming Language :: C
Classifier: License :: OSI Approved :: GNU General Public License v3 (GPLv3)
Classifier: Operating System :: OS Independent
Classifier: Topic :: Software Development
Classifier: Topic :: Software Development :: Build Tools
Classifier: Topic :: Software Development :: Embedded Systems
Classifier: Topic :: System :: Software Distribution
Requires-Python: >=3.7
License-File: LICENSE
Requires-Dist: urllib3
Requires-Dist: requests
Requires-Dist: docker
Requires-Dist: ninja
Requires-Dist: cmake
Requires-Dist: semver
Requires-Dist: ruamel.yaml (>=0.17.17)
Requires-Dist: six
Provides-Extra: testing
Requires-Dist: pytest ; extra == 'testing'
Requires-Dist: mock ; extra == 'testing'
Requires-Dist: werkzeug ; extra == 'testing'
Requires-Dist: Flask ; extra == 'testing'
